<?xml version="1.0" encoding="UTF-8"?>
<MF0 version="1.1" packageUris="http://schema.mathworks.com/mf0/ci/19700101 http://schema.mathworks.com/mf0/sl_modelref_info/R2023a http://schema.mathworks.com/mf0/slexec_mm_sto/R2023a_202208151321 http://schema.mathworks.com/mf0/sltp_mm/R2023a_202209151115">
  <ModelRefInfoRepo.ModelRefInfoRoot type="ModelRefInfoRepo.ModelRefInfoRoot" uuid="0baca9a3-8fdc-4396-a785-fdbe101a6a80">
    <JITEngines>s1I6w4BXmlzc2WC2pW2UWBB</JITEngines>
    <JITEngines>s3DDpLpSOKnWhXEp5DFlHo</JITEngines>
    <JITEngines>sJP9bwtMbhHOkbHhVvreLBF</JITEngines>
    <JITEngines>sVVC1X4UMt6s3VuUtwan8y</JITEngines>
    <calibrationData type="ModelRefInfoRepo.CalibrationData" uuid="74b1a71f-0093-4abb-a234-8d2cd384eb79">
      <InternalData>[{&quot;Name&quot;:&quot;&quot;,&quot;Profile&quot;:&quot;&quot;},{&quot;Name&quot;:&quot;&quot;,&quot;Profile&quot;:&quot;&quot;},{&quot;Name&quot;:&quot;&quot;,&quot;Profile&quot;:&quot;&quot;},{&quot;Name&quot;:&quot;&quot;,&quot;Profile&quot;:&quot;&quot;},{&quot;Name&quot;:&quot;&quot;,&quot;Profile&quot;:&quot;&quot;},{&quot;Name&quot;:&quot;&quot;,&quot;Profile&quot;:&quot;&quot;},{&quot;Name&quot;:&quot;&quot;,&quot;Profile&quot;:&quot;&quot;},{&quot;Name&quot;:&quot;&quot;,&quot;Profile&quot;:&quot;&quot;},{&quot;Name&quot;:&quot;&quot;,&quot;Profile&quot;:&quot;&quot;},{&quot;Name&quot;:&quot;&quot;,&quot;Profile&quot;:&quot;&quot;},{&quot;Name&quot;:&quot;&quot;,&quot;Profile&quot;:&quot;&quot;},{&quot;Name&quot;:&quot;&quot;,&quot;Profile&quot;:&quot;&quot;},{&quot;Name&quot;:&quot;&quot;,&quot;Profile&quot;:&quot;&quot;},{&quot;Name&quot;:&quot;&quot;,&quot;Profile&quot;:&quot;&quot;}]</InternalData>
      <ModelName>ATTN</ModelName>
    </calibrationData>
    <childModelRefInfo type="ModelRefInfoRepo.ChildModelRefInfo" uuid="4cb8f6bc-b2c3-4371-8355-59574e428ba7">
      <modelName>ATTN</modelName>
      <modelPath>ATTN</modelPath>
    </childModelRefInfo>
    <clockResolutions type="ModelRefInfoRepo.ClockResolutionInfo" uuid="33bdaa3d-df89-43a5-ab78-f8999b713ea8">
      <rateIdx>1</rateIdx>
      <resolution>.001</resolution>
      <source>DeducedFromSampleTime</source>
    </clockResolutions>
    <dataTransferInfos>AAFJTQAAAAAOAAAAOAAAAAYAAAAIAAAAAgAAAAAAAAAFAAAACAAAAAAAAAABAAAAAQAAAAAAAAAFAAQAAQAAAAEAAAAAAAAA</dataTransferInfos>
    <defaultsCMapping>{&quot;Inports&quot;:&quot;{\&quot;Name\&quot;:\&quot;Default\&quot;,\&quot;Checksum\&quot;:\&quot;Default\&quot;,\&quot;PerInstancePropertiesChecksum\&quot;:\&quot;\&quot;,\&quot;MemorySectionName\&quot;:\&quot;None\&quot;,\&quot;MemorySectionChecksum\&quot;:\&quot;None\&quot;}&quot;,&quot;Outports&quot;:&quot;{\&quot;Name\&quot;:\&quot;Default\&quot;,\&quot;Checksum\&quot;:\&quot;Default\&quot;,\&quot;PerInstancePropertiesChecksum\&quot;:\&quot;\&quot;,\&quot;MemorySectionName\&quot;:\&quot;None\&quot;,\&quot;MemorySectionChecksum\&quot;:\&quot;None\&quot;}&quot;,&quot;ParameterArguments&quot;:&quot;{\&quot;Name\&quot;:\&quot;Default\&quot;,\&quot;Checksum\&quot;:\&quot;Default\&quot;,\&quot;PerInstancePropertiesChecksum\&quot;:\&quot;\&quot;,\&quot;MemorySectionName\&quot;:\&quot;None\&quot;,\&quot;MemorySectionChecksum\&quot;:\&quot;None\&quot;}&quot;,&quot;LocalParameters&quot;:&quot;{\&quot;Name\&quot;:\&quot;PageSwitching\&quot;,\&quot;Checksum\&quot;:\&quot;1969678929\&quot;,\&quot;PerInstancePropertiesChecksum\&quot;:\&quot;\&quot;,\&quot;MemorySectionName\&quot;:\&quot;None\&quot;,\&quot;MemorySectionChecksum\&quot;:\&quot;None\&quot;}&quot;,&quot;GlobalParameters&quot;:&quot;{\&quot;Name\&quot;:\&quot;slrealtime_PageSwitching\&quot;,\&quot;Checksum\&quot;:\&quot;673606011\&quot;,\&quot;PerInstancePropertiesChecksum\&quot;:\&quot;\&quot;,\&quot;MemorySectionName\&quot;:\&quot;None\&quot;,\&quot;MemorySectionChecksum\&quot;:\&quot;None\&quot;}&quot;,&quot;InternalData&quot;:&quot;{\&quot;Name\&quot;:\&quot;Default\&quot;,\&quot;Checksum\&quot;:\&quot;Default\&quot;,\&quot;PerInstancePropertiesChecksum\&quot;:\&quot;\&quot;,\&quot;MemorySectionName\&quot;:\&quot;None\&quot;,\&quot;MemorySectionChecksum\&quot;:\&quot;None\&quot;}&quot;,&quot;SharedLocalDataStores&quot;:&quot;{\&quot;Name\&quot;:\&quot;Default\&quot;,\&quot;Checksum\&quot;:\&quot;Default\&quot;,\&quot;PerInstancePropertiesChecksum\&quot;:\&quot;\&quot;,\&quot;MemorySectionName\&quot;:\&quot;None\&quot;,\&quot;MemorySectionChecksum\&quot;:\&quot;None\&quot;}&quot;,&quot;GlobalDataStores&quot;:&quot;{\&quot;Name\&quot;:\&quot;Default\&quot;,\&quot;Checksum\&quot;:\&quot;Default\&quot;,\&quot;PerInstancePropertiesChecksum\&quot;:\&quot;\&quot;,\&quot;MemorySectionName\&quot;:\&quot;None\&quot;,\&quot;MemorySectionChecksum\&quot;:\&quot;None\&quot;}&quot;,&quot;Constants&quot;:&quot;{\&quot;Name\&quot;:\&quot;Default\&quot;,\&quot;Checksum\&quot;:\&quot;Default\&quot;,\&quot;PerInstancePropertiesChecksum\&quot;:\&quot;\&quot;,\&quot;MemorySectionName\&quot;:\&quot;None\&quot;,\&quot;MemorySectionChecksum\&quot;:\&quot;None\&quot;}&quot;,&quot;DataTransfers&quot;:&quot;{\&quot;Name\&quot;:\&quot;Default\&quot;,\&quot;Checksum\&quot;:\&quot;Default\&quot;,\&quot;PerInstancePropertiesChecksum\&quot;:\&quot;\&quot;,\&quot;MemorySectionName\&quot;:\&quot;None\&quot;,\&quot;MemorySectionChecksum\&quot;:\&quot;None\&quot;}&quot;,&quot;ModelData&quot;:&quot;{\&quot;Name\&quot;:\&quot;Default\&quot;,\&quot;Checksum\&quot;:\&quot;Default\&quot;,\&quot;PerInstancePropertiesChecksum\&quot;:\&quot;\&quot;,\&quot;MemorySectionName\&quot;:\&quot;None\&quot;,\&quot;MemorySectionChecksum\&quot;:\&quot;None\&quot;}&quot;,&quot;InitializeTerminate&quot;:&quot;{\&quot;Name\&quot;:\&quot;Default\&quot;,\&quot;Checksum\&quot;:\&quot;Default\&quot;,\&quot;PerInstancePropertiesChecksum\&quot;:\&quot;\&quot;,\&quot;MemorySectionName\&quot;:\&quot;None\&quot;,\&quot;MemorySectionChecksum\&quot;:\&quot;None\&quot;}&quot;,&quot;Execution&quot;:&quot;{\&quot;Name\&quot;:\&quot;Default\&quot;,\&quot;Checksum\&quot;:\&quot;Default\&quot;,\&quot;PerInstancePropertiesChecksum\&quot;:\&quot;\&quot;,\&quot;MemorySectionName\&quot;:\&quot;None\&quot;,\&quot;MemorySectionChecksum\&quot;:\&quot;None\&quot;}&quot;,&quot;SharedUtility&quot;:&quot;{\&quot;Name\&quot;:\&quot;Default\&quot;,\&quot;Checksum\&quot;:\&quot;Default\&quot;,\&quot;PerInstancePropertiesChecksum\&quot;:\&quot;\&quot;,\&quot;MemorySectionName\&quot;:\&quot;None\&quot;,\&quot;MemorySectionChecksum\&quot;:\&quot;None\&quot;}&quot;}</defaultsCMapping>
    <fastestNoncontSigFeedingDerivPorts>-1.0</fastestNoncontSigFeedingDerivPorts>
    <hasBlockWithPeriodicDiscreteSampleTime>true</hasBlockWithPeriodicDiscreteSampleTime>
    <hasBwsAccessed>true</hasBwsAccessed>
    <hasBwsAccessedByAnyModel>true</hasBwsAccessedByAnyModel>
    <hasContinuousSampleTime>true</hasContinuousSampleTime>
    <hasSignalLogging>true</hasSignalLogging>
    <hasStatesModifiedInOutputUpdate>true</hasStatesModifiedInOutputUpdate>
    <isBdInSimModeForSimCodegenVariants>false</isBdInSimModeForSimCodegenVariants>
    <loggingSaveFormat>4</loggingSaveFormat>
    <maxFreqHz>-1.0</maxFreqHz>
    <needAbsoluteTimeDisallowInitPort>true</needAbsoluteTimeDisallowInitPort>
    <nonTunableVariables>SampleTime</nonTunableVariables>
    <numDataInputPorts>0</numDataInputPorts>
    <numLoggableJacobianDStates>0</numLoggableJacobianDStates>
    <runtimeNonFcnCallRateInfos type="ModelRefInfoRepo.RateInfo">
      <compiled>true</compiled>
      <needAbsoluteTime>true</needAbsoluteTime>
      <period>0.0</period>
      <priority>40</priority>
      <rateIdx>0</rateIdx>
    </runtimeNonFcnCallRateInfos>
    <runtimeNonFcnCallRateInfos type="ModelRefInfoRepo.RateInfo">
      <compiled>true</compiled>
      <needAbsoluteTime>true</needAbsoluteTime>
      <nonFcnCallPartitionName>Cont</nonFcnCallPartitionName>
      <period>.001</period>
      <priority>40</priority>
      <rateIdx>1</rateIdx>
    </runtimeNonFcnCallRateInfos>
    <sampleTimeInheritanceRule>2</sampleTimeInheritanceRule>
    <solverStatusFlags>335</solverStatusFlags>
    <timingAndTaskingRegistry>&lt;?xml version=&quot;1.0&quot;?&gt;
&lt;slexec_sto version=&quot;1.1&quot; packageUris=&quot;http://schema.mathworks.com/mf0/slexec_mm_sto/R2023a_202208151321&quot;&gt;
  &lt;sto.Registry type=&quot;sto.Registry&quot; uuid=&quot;1452af82-88ce-4fef-94f1-1f2875e43077&quot;&gt;
    &lt;executionSpec&gt;Undetermined&lt;/executionSpec&gt;
    &lt;identifier&gt;ATTN&lt;/identifier&gt;
    &lt;clockRegistry type=&quot;sto.ClockRegistry&quot; uuid=&quot;0778a8fb-7f70-459d-9cd0-bf9187e7bb82&quot;&gt;
      &lt;clocks type=&quot;sto.Timer&quot; uuid=&quot;6be10344-3da7-42e6-9beb-38e4eafdd0ce&quot;&gt;
        &lt;clockTickConstraint&gt;PeriodicWithFixedResolution&lt;/clockTickConstraint&gt;
        &lt;computedFundamentalDiscretePeriod&gt;.001&lt;/computedFundamentalDiscretePeriod&gt;
        &lt;fastestDiscreteRate type=&quot;sto.ClassicPeriodicDiscreteRate&quot; uuid=&quot;b912ae9a-941d-43ae-bdf4-09757b38cc6d&quot;/&gt;
        &lt;isDefaultTimer&gt;true&lt;/isDefaultTimer&gt;
        &lt;resolution&gt;.001&lt;/resolution&gt;
        &lt;timeAdvanceMode&gt;FixedStep&lt;/timeAdvanceMode&gt;
        &lt;identifier&gt;ATTN::defaultTimer&lt;/identifier&gt;
        &lt;rates type=&quot;sto.ContinuousRate&quot; uuid=&quot;567e4c4f-7902-4c2a-b7e0-5d235a7a7173&quot;&gt;
          &lt;annotation&gt;Cont&lt;/annotation&gt;
          &lt;clockId&gt;ATTN::defaultTimer&lt;/clockId&gt;
          &lt;description&gt;Continuous&lt;/description&gt;
          &lt;taskId&gt;_task0&lt;/taskId&gt;
          &lt;rateSpec type=&quot;sto.RateSpec&quot; uuid=&quot;c364eb6a-033e-4667-b247-dc4f9d41e897&quot;/&gt;
        &lt;/rates&gt;
        &lt;rates type=&quot;sto.ClassicPeriodicDiscreteRate&quot; uuid=&quot;b912ae9a-941d-43ae-bdf4-09757b38cc6d&quot;&gt;
          &lt;annotation&gt;D1&lt;/annotation&gt;
          &lt;clockId&gt;ATTN::defaultTimer&lt;/clockId&gt;
          &lt;colorIndex&gt;2&lt;/colorIndex&gt;
          &lt;description&gt;Discrete 1&lt;/description&gt;
          &lt;rateIdx&gt;1&lt;/rateIdx&gt;
          &lt;taskId&gt;_task0&lt;/taskId&gt;
          &lt;rateSpec type=&quot;sto.RateSpec&quot; uuid=&quot;b55f0dba-0e80-4da5-b561-3c066e9a9687&quot;&gt;
            &lt;period&gt;.001&lt;/period&gt;
            &lt;rateType&gt;ClassicPeriodicDiscrete&lt;/rateType&gt;
          &lt;/rateSpec&gt;
        &lt;/rates&gt;
        &lt;baseRate type=&quot;sto.ContinuousRate&quot; uuid=&quot;9966f226-4c47-41aa-9283-881e8e55bffa&quot;&gt;
          &lt;annotation&gt;Cont&lt;/annotation&gt;
          &lt;clockId&gt;ATTN::defaultTimer&lt;/clockId&gt;
          &lt;description&gt;Continuous&lt;/description&gt;
          &lt;taskId&gt;_task0&lt;/taskId&gt;
          &lt;rateSpec type=&quot;sto.RateSpec&quot; uuid=&quot;22f9f7b1-55e8-41b6-8cbc-8b8ceebc00e2&quot;/&gt;
        &lt;/baseRate&gt;
      &lt;/clocks&gt;
      &lt;clocks type=&quot;sto.Event&quot; uuid=&quot;01c445d9-7c19-41f6-be0b-c9069123a3a4&quot;&gt;
        &lt;eventType&gt;PARAMETER_CHANGE_EVENT&lt;/eventType&gt;
        &lt;cNum&gt;1&lt;/cNum&gt;
        &lt;clockType&gt;Event&lt;/clockType&gt;
        &lt;identifier&gt;ParameterChangeEvent&lt;/identifier&gt;
        &lt;rates type=&quot;sto.ModelWideEventRate&quot; uuid=&quot;4ade08b8-0514-4718-b5a8-67ec07d53eec&quot;&gt;
          &lt;clockId&gt;ParameterChangeEvent&lt;/clockId&gt;
          &lt;rateIdx&gt;-1&lt;/rateIdx&gt;
          &lt;taskId&gt;ModelWideParameterChangeEvent&lt;/taskId&gt;
          &lt;useForExecution&gt;NotForExecution&lt;/useForExecution&gt;
          &lt;rateSpec type=&quot;sto.RateSpec&quot; uuid=&quot;27225fbc-8f23-4939-b290-d25c45c4b5aa&quot;&gt;
            &lt;period&gt;inf&lt;/period&gt;
            &lt;rateType&gt;ModelWideParameterChangeEvent&lt;/rateType&gt;
          &lt;/rateSpec&gt;
        &lt;/rates&gt;
      &lt;/clocks&gt;
      &lt;timeAdvanceMode&gt;FixedStep&lt;/timeAdvanceMode&gt;
    &lt;/clockRegistry&gt;
    &lt;taskRegistry type=&quot;sto.TaskRegistry&quot; uuid=&quot;e36d9d7b-a642-4a66-87d1-27243bd3b2d9&quot;&gt;
      &lt;rootTaskHierarchyElements type=&quot;sto.Task&quot; uuid=&quot;c5453301-57af-4943-bacb-6cfc67e28afd&quot;&gt;
        &lt;isExplicit&gt;true&lt;/isExplicit&gt;
        &lt;rates type=&quot;sto.ModelWideEventRate&quot; uuid=&quot;0206dbbd-b6e4-47cf-976b-b617472ec102&quot;&gt;
          &lt;clockId&gt;ParameterChangeEvent&lt;/clockId&gt;
          &lt;rateIdx&gt;-1&lt;/rateIdx&gt;
          &lt;taskId&gt;ModelWideParameterChangeEvent&lt;/taskId&gt;
          &lt;useForExecution&gt;NotForExecution&lt;/useForExecution&gt;
          &lt;rateSpec type=&quot;sto.RateSpec&quot; uuid=&quot;6a1206a5-4d18-47a5-abaa-4b288db41a1c&quot;&gt;
            &lt;period&gt;inf&lt;/period&gt;
            &lt;rateType&gt;ModelWideParameterChangeEvent&lt;/rateType&gt;
          &lt;/rateSpec&gt;
        &lt;/rates&gt;
        &lt;schedulingClockId&gt;ParameterChangeEvent&lt;/schedulingClockId&gt;
        &lt;timeKeeperClockId&gt;ATTN::defaultTimer&lt;/timeKeeperClockId&gt;
        &lt;elementType&gt;Task&lt;/elementType&gt;
        &lt;identifier&gt;ModelWideParameterChangeEvent&lt;/identifier&gt;
        &lt;priority&gt;-1&lt;/priority&gt;
      &lt;/rootTaskHierarchyElements&gt;
      &lt;rootTaskHierarchyElements type=&quot;sto.Task&quot; uuid=&quot;4f9665a4-78fb-4059-8e0c-2991c4dfa275&quot;&gt;
        &lt;isExecutable&gt;true&lt;/isExecutable&gt;
        &lt;orderIndex&gt;1&lt;/orderIndex&gt;
        &lt;rates type=&quot;sto.ContinuousRate&quot; uuid=&quot;573857c5-d5f1-493c-95c9-4987dbdec765&quot;&gt;
          &lt;annotation&gt;Cont&lt;/annotation&gt;
          &lt;clockId&gt;ATTN::defaultTimer&lt;/clockId&gt;
          &lt;description&gt;Continuous&lt;/description&gt;
          &lt;taskId&gt;_task0&lt;/taskId&gt;
          &lt;rateSpec type=&quot;sto.RateSpec&quot; uuid=&quot;f17bd79d-73b6-4fc7-a53a-d5f1a9dda776&quot;/&gt;
        &lt;/rates&gt;
        &lt;rates type=&quot;sto.ClassicPeriodicDiscreteRate&quot; uuid=&quot;138dfed6-f7aa-45cd-801b-20c1b6987638&quot;&gt;
          &lt;annotation&gt;D1&lt;/annotation&gt;
          &lt;clockId&gt;ATTN::defaultTimer&lt;/clockId&gt;
          &lt;colorIndex&gt;2&lt;/colorIndex&gt;
          &lt;description&gt;Discrete 1&lt;/description&gt;
          &lt;rateIdx&gt;1&lt;/rateIdx&gt;
          &lt;taskId&gt;_task0&lt;/taskId&gt;
          &lt;rateSpec type=&quot;sto.RateSpec&quot; uuid=&quot;c085dee4-9bd3-4bbe-b8ba-104f9283a9d1&quot;&gt;
            &lt;period&gt;.001&lt;/period&gt;
            &lt;rateType&gt;ClassicPeriodicDiscrete&lt;/rateType&gt;
          &lt;/rateSpec&gt;
        &lt;/rates&gt;
        &lt;schedulingClockId&gt;ATTN::defaultTimer&lt;/schedulingClockId&gt;
        &lt;timeKeeperClockId&gt;ATTN::defaultTimer&lt;/timeKeeperClockId&gt;
        &lt;elementType&gt;Task&lt;/elementType&gt;
        &lt;identifier&gt;_task0&lt;/identifier&gt;
        &lt;priority&gt;40&lt;/priority&gt;
      &lt;/rootTaskHierarchyElements&gt;
      &lt;taskDependencyGraph type=&quot;sto.SerializedTaskConnectionList&quot; uuid=&quot;0bb916c9-dda2-4f95-8914-4b24e47cec3e&quot;&gt;
        &lt;clockIdentifier&gt;ATTN::defaultTimer&lt;/clockIdentifier&gt;
        &lt;taskIdentifier&gt;_task0&lt;/taskIdentifier&gt;
      &lt;/taskDependencyGraph&gt;
      &lt;taskDependencyGraph type=&quot;sto.SerializedTaskConnectionList&quot; uuid=&quot;cf302c5d-dc63-4e4e-a8e9-18459abd638b&quot;&gt;
        &lt;clockIdentifier&gt;ParameterChangeEvent&lt;/clockIdentifier&gt;
        &lt;taskIdentifier&gt;ModelWideParameterChangeEvent&lt;/taskIdentifier&gt;
      &lt;/taskDependencyGraph&gt;
      &lt;taskingMode&gt;ClassicMultiTasking&lt;/taskingMode&gt;
    &lt;/taskRegistry&gt;
  &lt;/sto.Registry&gt;
&lt;/slexec_sto&gt;</timingAndTaskingRegistry>
    <FMUBlockMap type="ModelRefInfoRepo.FMUBlockInfo" uuid="ba7d0bd5-2b22-47ac-a744-4be4bb15de3e"/>
    <codeGenInfo type="ModelRefInfoRepo.CodeGenInformation" uuid="fa824021-87f3-4115-bacc-a857be2cf795"/>
    <compiledVariantInfos type="ModelRefInfoRepo.CompiledVariantInfoMap" uuid="7207785f-7733-4365-8e84-51c0175c1943"/>
    <configSettingsForConsistencyChecks type="ModelRefInfoRepo.ConfigSettingsForConsistencyChecks" uuid="44a43f6d-0f15-4e5d-a9b1-06a5128bf4a4">
      <concurrentTaskSupport>true</concurrentTaskSupport>
      <consistentOutportInitialization>true</consistentOutportInitialization>
      <fixedStepSize>.001</fixedStepSize>
      <frameDiagnosticSetting>2</frameDiagnosticSetting>
      <hasHybridSampleTime>true</hasHybridSampleTime>
      <signalLoggingSaveFormat>2</signalLoggingSaveFormat>
      <simSIMDOptimization>1</simSIMDOptimization>
      <solverName>FixedStepDiscrete</solverName>
      <solverType>SOLVER_TYPE_FIXEDSTEP</solverType>
      <hardwareSettings type="ModelRefInfoRepo.HardwareSettings" uuid="13cc6e18-921f-479a-98ba-a114abe5a892">
        <prodBitPerChar>8</prodBitPerChar>
        <prodBitPerDouble>64</prodBitPerDouble>
        <prodBitPerFloat>32</prodBitPerFloat>
        <prodBitPerInt>32</prodBitPerInt>
        <prodBitPerLong>64</prodBitPerLong>
        <prodBitPerLongLong>64</prodBitPerLongLong>
        <prodBitPerPointer>64</prodBitPerPointer>
        <prodBitPerPtrDiffT>64</prodBitPerPtrDiffT>
        <prodBitPerShort>16</prodBitPerShort>
        <prodBitPerSizeT>64</prodBitPerSizeT>
        <prodEndianess>1</prodEndianess>
        <prodLongLongMode>true</prodLongLongMode>
        <prodShiftRight>true</prodShiftRight>
        <prodWordSize>64</prodWordSize>
      </hardwareSettings>
    </configSettingsForConsistencyChecks>
    <controllableInputRatesMap type="ModelRefInfoRepo.VarTsUIDMap" uuid="37adf9a6-6af8-4310-9e46-108781228cf5"/>
    <controllableOutputRatesMap type="ModelRefInfoRepo.VarTsUIDMap" uuid="6d427ef8-e7c4-4342-b701-c7e7d7ae78b9"/>
    <dataPortGroup type="ModelRefInfoRepo.DataPortGroup" uuid="d253740e-aa29-479c-a822-4567cc0f3710"/>
    <expFcnUnconnectedDataPortGroup type="ModelRefInfoRepo.DataPortGroup" uuid="4bf65860-83d8-4714-be24-67398b83c985"/>
    <interfaceParameterInfo type="ModelRefInfoRepo.InterfaceParameterInfo" uuid="7e709d66-e615-4b39-bdd3-f63c769daf18"/>
    <messageInfo type="ModelRefInfoRepo.MessageInformation" uuid="d20ee485-a609-4ca1-ba7a-8f369ce7ae59"/>
    <methodInfo type="ModelRefInfoRepo.MethodExistenceInfo" uuid="cb18d9b7-0bb0-43ef-89f6-af57eb857457">
      <hasSystemInitializeMethod>true</hasSystemInitializeMethod>
      <hasSystemResetMethod>true</hasSystemResetMethod>
      <hasTerminateMethod>true</hasTerminateMethod>
      <hasUpdateMethod>true</hasUpdateMethod>
    </methodInfo>
    <periodicEventPortUnsupportedBlockInfo type="ModelRefInfoRepo.PeriodicEventPortUnsupportedBlockInfo" uuid="f3452814-dc04-48f6-9a73-d326b308c102"/>
    <portGroupsRequireSameRate type="ModelRefInfoRepo.PortGroupsRequireSameRate" uuid="2cf0e720-a0e3-4c97-bbe1-156deb777cea">
      <DSMPortGroups type="ModelRefInfoRepo.NameToPortGroupIdxVectMap" uuid="e3348ffe-bcd5-4280-af3c-2201f4579093"/>
      <GlobalDSMPortGroups type="ModelRefInfoRepo.NameToPortGroupIdxVectMap" uuid="09fa86e4-94ec-4c5f-ae4f-ee4cca1334ff"/>
      <mergedPortGroups type="ModelRefInfoRepo.NameToPortGroupIdxVectMap" uuid="47d16000-945e-4ab4-9589-e54c15ef0b87"/>
    </portGroupsRequireSameRate>
    <rateBasedMdlGlobalDSMRateSpec type="ModelRefInfoRepo.GlobalDSMRateSpecMap" uuid="ae6f1350-8e8c-4c92-964b-849ec89bef5f"/>
    <rateSpecOfGlobalDSMAccessedByDescExpFcnMdlMap type="ModelRefInfoRepo.GlobalDSMRateSpecMap" uuid="b1ff69a8-5737-4174-8064-9fc7f3254aa7"/>
    <rootBlockDiagramInterface type="ci.Model" uuid="5d8109d6-5f71-45b2-8de8-7dfb9e142ba9">
      <p_RootComponentInterface type="ci.ComponentInterface" uuid="2035a52c-afb2-4449-9d62-e90bd1da63f9">
        <p_Name>ATTN</p_Name>
        <p_Type>ROOT</p_Type>
      </p_RootComponentInterface>
    </rootBlockDiagramInterface>
    <simulinkFunctions type="ModelRefInfoRepo.SimulinkFunctions" uuid="64894d55-c027-44da-966c-54c32b12d66c">
      <compSimulinkFunctionCatalog></compSimulinkFunctionCatalog>
    </simulinkFunctions>
    <sltpContext type="sltp.mm.core.Context" uuid="eaa72d88-4ee5-416d-b060-e92534399baf">
      <defaultEventBehavior type="sltp.mm.core.EventBehavior" uuid="d7ab87b1-5e71-4ca0-9d82-f03c5bd9acc2"/>
      <editorState type="sltp.mm.core.EditorState" uuid="dfddbac0-357d-476b-aee8-f6ce847b5b79">
        <isSynchronized>true</isSynchronized>
        <panelState type="sltp.mm.core.EditorPanelState" uuid="ce5f0e47-f930-4581-a1d3-2284783b58ef"/>
      </editorState>
      <rootTask type="sltp.mm.core.Task" uuid="d68bf30b-f682-4bfc-92a1-8148c2d0e839">
        <context type="sltp.mm.core.Context" uuid="eaa72d88-4ee5-416d-b060-e92534399baf"/>
        <explicit>false</explicit>
        <name>Default</name>
        <priority>-2147483648</priority>
        <subgraph type="sltp.mm.core.Graph" uuid="d49cbe55-bd86-4672-a486-46c034e89138">
          <tasks type="sltp.mm.core.Task" uuid="df1a1675-8ecf-4b80-b806-ca51f6c69f82">
            <baseTask>true</baseTask>
            <context type="sltp.mm.core.Context" uuid="eaa72d88-4ee5-416d-b060-e92534399baf"/>
            <explicit>false</explicit>
            <id>1</id>
            <isTimed>true</isTimed>
            <name>Cont</name>
            <priority>40</priority>
            <rates type="sltp.mm.core.Rate" uuid="058ac3ba-ac1f-4840-9bf8-7aeb48fd531c">
              <annotation>Cont</annotation>
              <color>255</color>
              <hasBlocks>true</hasBlocks>
              <identifier>Continuous00</identifier>
              <rateIndex>0</rateIndex>
              <rateSpec type="sltp.mm.core.RateSpec">
                <period>0.0</period>
              </rateSpec>
              <sti>0</sti>
            </rates>
            <rates type="sltp.mm.core.Rate" uuid="526607dc-17c6-4055-9600-4f015f126818">
              <annotation>D1</annotation>
              <color>-436207361</color>
              <hasBlocks>true</hasBlocks>
              <rateIndex>1</rateIndex>
              <rateSpec type="sltp.mm.core.RateSpec">
                <period>.001</period>
              </rateSpec>
              <sti>1</sti>
            </rates>
          </tasks>
        </subgraph>
      </rootTask>
    </sltpContext>
    <stateWriterToOwnerMap type="ModelRefInfoRepo.StateWriterInfo" uuid="f7e481aa-d5d8-4536-8f45-2dd1bf839688"/>
    <stoClientDataRegistry type="sto.ClientDataRegistry" uuid="ef60c6ce-d81b-436d-a9bc-740307f9e53f">
      <dataSets type="sto.ClientClockNamedDataSet" uuid="b2cb6134-d88c-496f-b31c-5f00513592ad">
        <tag>sltpEvents</tag>
      </dataSets>
      <dataSets type="sto.ClientTaskHierarchyElementNamedDataSet" uuid="c45218f5-c170-4b90-8555-64087d9502e3">
        <tag>sltpTaskGroups</tag>
      </dataSets>
      <dataSets type="sto.ClientTaskHierarchyElementNamedDataSet" uuid="47f7ca22-eec6-48da-a8bb-04914a6a89de">
        <dSet type="ModelRefInfoRepo.SltpTaskData" uuid="2317c7cd-6c49-45fa-a9d6-0ca421ef51c5"/>
        <tSet type="ModelRefInfoRepo.SltpTaskData" uuid="2317c7cd-6c49-45fa-a9d6-0ca421ef51c5">
          <dataName>Cont</dataName>
          <linkedSet type="sto.ClientTaskHierarchyElementNamedDataSet" uuid="47f7ca22-eec6-48da-a8bb-04914a6a89de"/>
          <id type="sto.TaskHierarchyElementId">
            <clockId>ATTN::defaultTimer</clockId>
            <id>_task0</id>
          </id>
        </tSet>
        <tag>sltpTasks</tag>
      </dataSets>
    </stoClientDataRegistry>
    <varTsUIDMap type="ModelRefInfoRepo.VarTsUIDMap" uuid="fe322a88-8320-46fa-887e-f4b61e0f7e38"/>
  </ModelRefInfoRepo.ModelRefInfoRoot>
</MF0>